platypos/__init__.py
platypos/beta_K_functions.py
platypos/lx_evo_and_flux.py
platypos/mass_evolution_function.py
platypos/mass_loss_rate_function.py
platypos/mass_luminosity_relation.py
platypos/notify.py
platypos/planet_LoFo14.py
platypos/planet_LoFo14_PAPER.py
platypos/planet_Ot20.py
platypos/planet_Ot20_PAPER.py
platypos/planet_model_Ot20.py
platypos/planet_models_LoFo14.py
platypos-1.1.16.dist-info/LICENSE
platypos-1.1.16.dist-info/METADATA
platypos-1.1.16.dist-info/WHEEL
platypos-1.1.16.dist-info/top_level.txt
platypos-1.1.16.dist-info/RECORD
