Metadata-Version: 2.1
Name: platypos
Version: 1.1.16
Summary: PLAneTarY PhOtoevaporation Simulator
Home-page: https://github.com/lketzer/platypos
Author: Laura Ketzer
Author-email: lketzer@aip.de
License: UNKNOWN
Keywords: astronomy,exoplanets,...
Platform: UNKNOWN
Classifier: Programming Language :: Python :: 3
Classifier: Development Status :: 3 - Alpha
Classifier: Environment :: Console
Classifier: License :: OSI Approved :: MIT License
Classifier: Operating System :: OS Independent
Requires-Python: >=3.6
Requires-Dist: astropy
Requires-Dist: matplotlib
Requires-Dist: numpy
Requires-Dist: pandas
Requires-Dist: scipy
Requires-Dist: astroquery
Requires-Dist: jupyter
Requires-Dist: PyAstronomy
Requires-Dist: sklearn
